codehackscalculatortest/__init__.py
codehackscalculatortest-0.0.1.dist-info/METADATA
codehackscalculatortest-0.0.1.dist-info/WHEEL
codehackscalculatortest-0.0.1.dist-info/top_level.txt
codehackscalculatortest-0.0.1.dist-info/RECORD
