Metadata-Version: 2.1
Name: codehackscalculatortest
Version: 0.0.1
Summary: Test create package
Home-page: UNKNOWN
Author: dhonyabumuhammad (Jakarta)
Author-email: <dp20bp@gmail.com>
License: UNKNOWN
Platform: UNKNOWN
Classifier: Programming Language :: Python :: 3
Classifier: Operating System :: Unix
Classifier: Operating System :: MacOS :: MacOS X
Classifier: Operating System :: Microsoft :: Windows
